trestle/__init__.py
trestle/__main__.py
trestle/cli.py
trestle/py.typed
trestle/common/__init__.py
trestle/common/common_types.py
trestle/common/const.py
trestle/common/err.py
trestle/common/file_utils.py
trestle/common/list_utils.py
trestle/common/load_validate.py
trestle/common/log.py
trestle/common/model_utils.py
trestle/common/str_utils.py
trestle/common/trash.py
trestle/common/type_utils.py
trestle/core/__init__.py
trestle/core/all_validator.py
trestle/core/base_model.py
trestle/core/catalog_validator.py
trestle/core/control_context.py
trestle/core/control_interface.py
trestle/core/control_reader.py
trestle/core/control_writer.py
trestle/core/docs_control_writer.py
trestle/core/draw_io.py
trestle/core/duplicates_validator.py
trestle/core/generators.py
trestle/core/generic_oscal.py
trestle/core/links_validator.py
trestle/core/object_factory.py
trestle/core/parser.py
trestle/core/pipeline.py
trestle/core/plugins.py
trestle/core/profile_resolver.py
trestle/core/py.typed
trestle/core/refs_validator.py
trestle/core/repository.py
trestle/core/rule_parameters_validator.py
trestle/core/ssp_io.py
trestle/core/trestle_base_model.py
trestle/core/validator.py
trestle/core/validator_factory.py
trestle/core/catalog/__init__.py
trestle/core/catalog/catalog_api.py
trestle/core/catalog/catalog_interface.py
trestle/core/catalog/catalog_merger.py
trestle/core/catalog/catalog_reader.py
trestle/core/catalog/catalog_writer.py
trestle/core/commands/__init__.py
trestle/core/commands/add.py
trestle/core/commands/assemble.py
trestle/core/commands/command_docs.py
trestle/core/commands/create.py
trestle/core/commands/describe.py
trestle/core/commands/href.py
trestle/core/commands/import_.py
trestle/core/commands/init.py
trestle/core/commands/merge.py
trestle/core/commands/partial_object_validate.py
trestle/core/commands/py.typed
trestle/core/commands/remove.py
trestle/core/commands/replicate.py
trestle/core/commands/split.py
trestle/core/commands/task.py
trestle/core/commands/validate.py
compliance_trestle-3.11.0.dist-info/METADATA
compliance_trestle-3.11.0.dist-info/WHEEL
compliance_trestle-3.11.0.dist-info/entry_points.txt
compliance_trestle-3.11.0.dist-info/licenses/LICENSE
compliance_trestle-3.11.0.dist-info/RECORD
