Metadata-Version: 2.4
Name: compliance-trestle
Version: 3.11.0
Summary: Tools to manage & autogenerate python objects representing the OSCAL layers/models
Project-URL: Homepage, https://oscal-compass.github.io/compliance-trestle
Project-URL: Documentation, https://oscal-compass.github.io/compliance-trestle
Project-URL: Source code, https://github.com/oscal-compass/compliance-trestle
Author-email: OSCAL Compass <oscal-compass-oversight@googlegroups.com>
License-Expression: Apache-2.0
License-File: LICENSE
Keywords: Compliance,OSCAL,Security
Classifier: Development Status :: 5 - Production/Stable
Classifier: Environment :: Console
Classifier: Intended Audience :: Developers
Classifier: Intended Audience :: Information Technology
Classifier: License :: OSI Approved :: Apache Software License
Classifier: Operating System :: Microsoft
Classifier: Operating System :: POSIX
Classifier: Programming Language :: Python :: 3
Classifier: Programming Language :: Python :: 3.9
Classifier: Programming Language :: Python :: 3.10
Classifier: Programming Language :: Python :: 3.11
Classifier: Programming Language :: Python :: 3.12
Requires-Python: >=3.9
Requires-Dist: attrs
Requires-Dist: cmarkgfm<2025.11,>=2024.1
Requires-Dist: cryptography==46.0.3
Requires-Dist: defusedxml
Requires-Dist: furl
Requires-Dist: ilcli
Requires-Dist: importlib-resources
Requires-Dist: jinja2==3.1.6
Requires-Dist: openpyxl~=3.0
Requires-Dist: orjson
Requires-Dist: paramiko==4.0.0
Requires-Dist: pydantic[email]>=2.0.0
Requires-Dist: python-dotenv>=0.10.4
Requires-Dist: python-frontmatter
Requires-Dist: pywin32>=1.0; platform_system == 'Windows'
Requires-Dist: requests>=2.32.2
Requires-Dist: ruamel-yaml
Provides-Extra: dev
Requires-Dist: cairosvg; extra == 'dev'
Requires-Dist: datamodel-code-generator[http]==0.36.0; extra == 'dev'
Requires-Dist: gitpython; extra == 'dev'
Requires-Dist: livereload; extra == 'dev'
Requires-Dist: markdown-include; extra == 'dev'
Requires-Dist: mike; extra == 'dev'
Requires-Dist: mkdocs-awesome-pages-plugin; extra == 'dev'
Requires-Dist: mkdocs-git-revision-date-localized-plugin; extra == 'dev'
Requires-Dist: mkdocs-htmlproofer-plugin; extra == 'dev'
Requires-Dist: mkdocs-material; extra == 'dev'
Requires-Dist: mkdocs-minify-plugin; extra == 'dev'
Requires-Dist: mkdocs>=1.6.0; extra == 'dev'
Requires-Dist: mkdocstrings[python]>=0.25.2; extra == 'dev'
Requires-Dist: mypy; extra == 'dev'
Requires-Dist: pillow; extra == 'dev'
Requires-Dist: pre-commit>=2.4.0; extra == 'dev'
Requires-Dist: pylint; extra == 'dev'
Requires-Dist: pymdown-extensions; extra == 'dev'
Requires-Dist: python-semantic-release>=10.4.0; extra == 'dev'
Requires-Dist: types-paramiko; extra == 'dev'
Requires-Dist: types-pyyaml; extra == 'dev'
Requires-Dist: types-requests; extra == 'dev'
Requires-Dist: types-setuptools; extra == 'dev'
Provides-Extra: docs
Requires-Dist: cairosvg; extra == 'docs'
Requires-Dist: livereload; extra == 'docs'
Requires-Dist: markdown-include; extra == 'docs'
Requires-Dist: mike; extra == 'docs'
Requires-Dist: mkdocs-awesome-pages-plugin; extra == 'docs'
Requires-Dist: mkdocs-git-revision-date-localized-plugin; extra == 'docs'
Requires-Dist: mkdocs-htmlproofer-plugin; extra == 'docs'
Requires-Dist: mkdocs-material; extra == 'docs'
Requires-Dist: mkdocs-minify-plugin; extra == 'docs'
Requires-Dist: mkdocs>=1.6.0; extra == 'docs'
Requires-Dist: mkdocstrings[python]>=0.25.2; extra == 'docs'
Requires-Dist: pillow; extra == 'docs'
Requires-Dist: pymdown-extensions; extra == 'docs'
Provides-Extra: typing
Requires-Dist: mypy; extra == 'typing'
Requires-Dist: types-paramiko; extra == 'typing'
Requires-Dist: types-pyyaml; extra == 'typing'
Requires-Dist: types-requests; extra == 'typing'
Requires-Dist: types-setuptools; extra == 'typing'
